nonebot_plugin_datastore/__init__.py
nonebot_plugin_datastore/compat.py
nonebot_plugin_datastore/config.py
nonebot_plugin_datastore/db.py
nonebot_plugin_datastore/plugin.py
nonebot_plugin_datastore/py.typed
nonebot_plugin_datastore/utils.py
nonebot_plugin_datastore/migrations/0f8d23241fd7_.py
nonebot_plugin_datastore/providers/__init__.py
nonebot_plugin_datastore/providers/database.py
nonebot_plugin_datastore/providers/json.py
nonebot_plugin_datastore/providers/toml.py
nonebot_plugin_datastore/providers/yaml.py
nonebot_plugin_datastore/script/__init__.py
nonebot_plugin_datastore/script/cli.py
nonebot_plugin_datastore/script/command.py
nonebot_plugin_datastore/script/utils.py
nonebot_plugin_datastore/script/migration/script.py.mako
nonebot_plugin_datastore-1.3.1.dist-info/METADATA
nonebot_plugin_datastore-1.3.1.dist-info/WHEEL
nonebot_plugin_datastore-1.3.1.dist-info/entry_points.txt
nonebot_plugin_datastore-1.3.1.dist-info/licenses/LICENSE
nonebot_plugin_datastore-1.3.1.dist-info/RECORD
