Metadata-Version: 2.4
Name: nonebot-plugin-datastore
Version: 1.3.1
Summary: 适用于 Nonebot2 的数据存储插件
Project-URL: Homepage, https://github.com/he0119/nonebot-plugin-datastore
Project-URL: Repository, https://github.com/he0119/nonebot-plugin-datastore.git
Project-URL: Issues, https://github.com/he0119/nonebot-plugin-datastore/issues
Project-URL: Changelog, https://github.com/he0119/nonebot-plugin-datastore/blob/main/CHANGELOG.md
Author-email: uy_sun <hmy0119@gmail.com>
License: MIT License
License-File: LICENSE
Requires-Python: >=3.9
Requires-Dist: alembic>=1.9.1
Requires-Dist: nonebot-plugin-localstore>=0.7.0
Requires-Dist: nonebot2[httpx]>=2.3.0
Requires-Dist: sqlalchemy[aiosqlite]>=2.0.0
Provides-Extra: all
Requires-Dist: anyio>=3.6.0; extra == 'all'
Requires-Dist: click>=8.0.0; extra == 'all'
Requires-Dist: pyyaml>=6.0.0; extra == 'all'
Requires-Dist: rtoml>=0.9.0; extra == 'all'
Requires-Dist: typing-extensions>=4.4.0; extra == 'all'
Provides-Extra: cli
Requires-Dist: anyio>=3.6.0; extra == 'cli'
Requires-Dist: click>=8.0.0; extra == 'cli'
Requires-Dist: typing-extensions>=4.4.0; extra == 'cli'
Provides-Extra: toml
Requires-Dist: rtoml>=0.9.0; extra == 'toml'
Provides-Extra: yaml
Requires-Dist: pyyaml>=6.0.0; extra == 'yaml'
